.editorconfig
.flake8
.gitignore
.travis.yml
CHANGELOG.md
LICENSE
Makefile
README.md
azure-pipelines.yml
setup.py
.github/workflows/test-all.yml
images/paramsurvey-graphite-graph.png
paramsurvey/__init__.py
paramsurvey/carbon.py
paramsurvey/examples.py
paramsurvey/params.py
paramsurvey/pslogger.py
paramsurvey/psmpi.py
paramsurvey/psmultiprocessing.py
paramsurvey/psray.py
paramsurvey/ray_debug_nodes.py
paramsurvey/stats.py
paramsurvey/utils.py
paramsurvey.egg-info/PKG-INFO
paramsurvey.egg-info/SOURCES.txt
paramsurvey.egg-info/dependency_links.txt
paramsurvey.egg-info/requires.txt
paramsurvey.egg-info/top_level.txt
scripts/paramsurvey-carbon-example.py
scripts/paramsurvey-cli.py
scripts/paramsurvey-greedy-example.py
scripts/paramsurvey-multistage-example.py
scripts/paramsurvey-readme-example.py
scripts/paramsurvey-rerun-missing.py
scripts/paramsurvey-stats-example.py
scripts/pset-creation-example.py
test/__pycache__/test_psmultiprocessing.cpython-36-pytest-5.3.2.pyc
test/integration/test-env-overrides.py
test/integration/test-generic_init_max_tasks_per_child.py
test/integration/test-multiprocessing-failure.py
test/integration/test-multiprocessing-nest.py
test/integration/test-multiprocessing-omp.py
test/integration/test-multiprocessing.sh
test/integration/test-only-builtins.py
test/integration/test-ray.sh
test/integration/test_generic.py
test/integration/test_stress.py
test/unit/test_multiprocessing.py
test/unit/test_params.py
test/unit/test_pslogger.py
test/unit/test_stats.py
test/unit/test_utils.py