Metadata-Version: 2.1
Name: paramsurvey
Version: 0.4.18
Summary: A toolkit for doing parameter surveys
Home-page: https://github.com/wumpus/paramsurvey
Author: Greg Lindahl and others
Author-email: lindahl@pbm.com
License: Apache 2.0
Classifier: Development Status :: 4 - Beta
Classifier: Environment :: Console
Classifier: Operating System :: POSIX :: Linux
Classifier: Environment :: MacOS X
Classifier: Intended Audience :: Information Technology
Classifier: Intended Audience :: Developers
Classifier: Natural Language :: English
Classifier: License :: OSI Approved :: Apache Software License
Classifier: Programming Language :: Python
Classifier: Programming Language :: Python :: 3.7
Classifier: Programming Language :: Python :: 3.8
Classifier: Programming Language :: Python :: 3.9
Classifier: Programming Language :: Python :: 3.10
Classifier: Programming Language :: Python :: 3.11
Classifier: Programming Language :: Python :: 3 :: Only
Requires-Python: >=3.7.*
Provides-Extra: ray
Provides-Extra: mpi
Provides-Extra: test
License-File: LICENSE
